<annotation>
	<folder>my-project-name</folder>
	<filename>IMG_5971.JPEG</filename>
	<path>/my-project-name/IMG_5971.JPEG</path>
	<source>
		<database>Unspecified</database>
	</source>
	<size>
		<width>1536</width>
		<height>2048</height>
		<depth>3</depth>
	</size>
	<object>
		<name>qrcode</name>
		<pose>Unspecified</pose>
		<truncated>0</truncated>
		<difficult>0</difficult>
		<bndbox>
			<xmin>977</xmin>
			<ymin>1475</ymin>
			<xmax>1206</xmax>
			<ymax>1678</ymax>
		</bndbox>
	</object>
	<object>
		<name>golden cheese</name>
		<pose>Unspecified</pose>
		<truncated>0</truncated>
		<difficult>0</difficult>
		<bndbox>
			<xmin>137</xmin>
			<ymin>630</ymin>
			<xmax>923</xmax>
			<ymax>1776</ymax>
		</bndbox>
	</object>
</annotation>